iterative/.iterative/config.yaml
iterative/.iterative/mkdocs.yml
iterative/.iterative/overrides/main.html
iterative/__init__.py
iterative/actions/project_actions.py
iterative/actions/test_actions.py
iterative/cli.py
iterative/cli_app_integration.py
iterative/config.py
iterative/docs/ai_action_system.md
iterative/docs/ai_iterative_assistant_chain_scenario.md
iterative/docs/api_errors.md
iterative/docs/example_goal.md
iterative/docs/execute_action_calls.md
iterative/docs/frontend_nextjs_project_structure.md
iterative/docs/index.md
iterative/docs/iter_agent_assistant_prompt.md
iterative/docs/iter_agent_game_prompt.md
iterative/docs/nosql_yorm.md
iterative/docs/simulation_experiments
iterative/docs/unit_tests_doc.md
iterative/mkdocs.yml
iterative/run_ngrok.sh
iterative/server_management.py
iterative/service/action_management/models/action.py
iterative/service/action_management/service/action_utils.py
iterative/service/action_management/tests/test_action_utils.py
iterative/service/api_management/service/api_utils.py
iterative/service/api_management/tests/test_api_utils.py
iterative/service/doc_management/service/doc_utils.py
iterative/service/doc_management/tests/test_doc_utils.py
iterative/service/model_management/models/iterative.py
iterative/service/model_management/service/model_utils.py
iterative/service/model_management/tests/test_model_utils.py
iterative/service/project_management/.iterative/config.yaml
iterative/service/project_management/models/project_models.py
iterative/service/project_management/service/import_utils.py
iterative/service/project_management/service/metadata_utils.py
iterative/service/project_management/service/project_utils.py
iterative/service/project_management/service/template_utils.py
iterative/service/project_management/templates/init/project_with_entry_template/.iterative/config.yaml
iterative/service/project_management/templates/init/project_with_entry_template/actions/your_starting_functions.py
iterative-1.1.4.dist-info/METADATA
iterative-1.1.4.dist-info/WHEEL
iterative-1.1.4.dist-info/entry_points.txt
iterative-1.1.4.dist-info/RECORD
